llmstudio/__init__.py
llmstudio/cli.py
llmstudio/langchain.py
llmstudio/providers/__init__.py
llmstudio/providers/provider.py
llmstudio/server.py
llmstudio/utils.py
llmstudio-1.0.6.dist-info/METADATA
llmstudio-1.0.6.dist-info/WHEEL
llmstudio-1.0.6.dist-info/entry_points.txt
llmstudio-1.0.6.dist-info/RECORD
