Metadata-Version: 2.3
Name: llmstudio
Version: 1.0.6
Summary: Prompt Perfection at Your Fingertips
License: MIT
Keywords: ml,ai,llm,llmops,openai,langchain,chatgpt,llmstudio,tensorops
Author: Cláudio Lemos
Author-email: claudio@tensorops.ai
Requires-Python: >=3.9,<3.13
Classifier: License :: OSI Approved :: MIT License
Classifier: Programming Language :: Python :: 3
Classifier: Programming Language :: Python :: 3.9
Classifier: Programming Language :: Python :: 3.10
Classifier: Programming Language :: Python :: 3.11
Classifier: Programming Language :: Python :: 3.12
Provides-Extra: proxy
Provides-Extra: tracker
Requires-Dist: langchain (>=0,<1)
Requires-Dist: langchain-experimental (>=0,<1)
Requires-Dist: llmstudio-core (>=1.0.0,<2.0.0)
Requires-Dist: llmstudio-proxy (>=1.0.1,<2.0.0) ; extra == "proxy"
Requires-Dist: llmstudio-tracker (>=1.1.0a0,<2.0.0) ; extra == "tracker"
Requires-Dist: pydantic (>=2.5,<3.0)
Requires-Dist: python-dotenv (>=0.4.0,<2.0.0)
Project-URL: Bug Tracker, https://github.com/tensoropsai/llmstudio/issues
Project-URL: Documentation, https://docs.llmstudio.ai
Project-URL: Homepage, https://llmstudio.ai/
Project-URL: Repository, https://github.com/tensoropsai/llmstudio
